homespeaker/__init__.py
homespeaker/main.py
homespeaker/screenwaker.py
homespeaker-1.0.0.dist-info/LICENSE
homespeaker-1.0.0.dist-info/METADATA
homespeaker-1.0.0.dist-info/WHEEL
homespeaker-1.0.0.dist-info/entry_points.txt
homespeaker-1.0.0.dist-info/top_level.txt
homespeaker-1.0.0.dist-info/RECORD
