Metadata-Version: 2.1
Name: homespeaker
Version: 1.0.0
Summary: Code to turn a laptop into a home speaker.
Author: ambauma
Author-email: ambauma@users.no-reply.github.com
License: GPLv3
Classifier: License :: OSI Approved :: GNU General Public License v3 (GPLv3)
Classifier: Intended Audience :: End Users/Desktop
Classifier: Environment :: X11 Applications
Classifier: Programming Language :: Python :: 3.10
Classifier: Topic :: Home Automation
License-File: LICENSE
Requires-Dist: playsound ~=1.3.0
Requires-Dist: pyyaml ~=6.0
Requires-Dist: fastapi
Requires-Dist: uvicorn[standard]
Provides-Extra: test
Requires-Dist: pydocstyle >=6.1.1 ; extra == 'test'
Requires-Dist: pytest >=7.0.1 ; extra == 'test'
Requires-Dist: pylint >=2.12.2 ; extra == 'test'
Requires-Dist: pytest-mockito >=0.0.4 ; extra == 'test'
Requires-Dist: pytest-cov >=3.0.0 ; extra == 'test'
Requires-Dist: black ; extra == 'test'
Requires-Dist: pydocstyle ; extra == 'test'
Requires-Dist: httpx ; extra == 'test'
